{ "links": [{"source": 0, "target": 27},
  {"source": 0, "target": 30},
  {"source": 0, "target": 10},
  {"source": 1, "target": 15},
  {"source": 1, "target": 23},
  {"source": 2, "target": 11},
  {"source": 2, "target": 19},
  {"source": 2, "target": 20},
  {"source": 2, "target": 17},
  {"source": 2, "target": 28},
  {"source": 3, "target": 23},
  {"source": 3, "target": 4},
  {"source": 4, "target": 23},
  {"source": 4, "target": 27},
  {"source": 4, "target": 13},
  {"source": 4, "target": 5},
  {"source": 4, "target": 21},
  {"source": 5, "target": 23},
  {"source": 6, "target": 16},
  {"source": 6, "target": 19},
  {"source": 6, "target": 18},
  {"source": 6, "target": 30},
  {"source": 7, "target": 30},
  {"source": 7, "target": 8},
  {"source": 7, "target": 29},
  {"source": 8, "target": 9},
  {"source": 8, "target": 30},
  {"source": 8, "target": 22},
  {"source": 8, "target": 16},
  {"source": 9, "target": 30},
  {"source": 9, "target": 22},
  {"source": 10, "target": 26},
  {"source": 11, "target": 16},
  {"source": 11, "target": 19},
  {"source": 11, "target": 20},
  {"source": 12, "target": 27},
  {"source": 12, "target": 30},
  {"source": 13, "target": 15},
  {"source": 13, "target": 23},
  {"source": 14, "target": 23},
  {"source": 14, "target": 25},
  {"source": 14, "target": 26},
  {"source": 15, "target": 23},
  {"source": 16, "target": 19},
  {"source": 16, "target": 30},
  {"source": 17, "target": 19},
  {"source": 17, "target": 23},
  {"source": 18, "target": 19},
  {"source": 18, "target": 24},
  {"source": 18, "target": 29},
  {"source": 19, "target": 25},
  {"source": 19, "target": 24},
  {"source": 20, "target": 28},
  {"source": 21, "target": 30},
  {"source": 21, "target": 23},
  {"source": 22, "target": 30},
  {"source": 23, "target": 25},
  {"source": 23, "target": 26},
  {"source": 23, "target": 27},
  {"source": 23, "target": 28}],
 "nodes": [{"id": "Canada"},
  {"id": "Brazil"},
  {"id": "Czech Republic"},
  {"id": "Luxembourg"},
  {"id": "France"},
  {"id": "Ireland"},
  {"id": "Norway"},
  {"id": "Israel"},
  {"id": "Australia"},
  {"id": "Iceland"},
  {"id": "United States"},
  {"id": "Slovenia"},
  {"id": "Chile"},
  {"id": "Belgium"},
  {"id": "Spain"},
  {"id": "Netherlands"},
  {"id": "Denmark"},
  {"id": "Poland"},
  {"id": "Finland"},
  {"id": "Sweden"},
  {"id": "Hungary"},
  {"id": "Switzerland"},
  {"id": "New Zealand"},
  {"id": "Germany"},
  {"id": "Estonia"},
  {"id": "Portugal"},
  {"id": "Mexico"},
  {"id": "United Kingdom"},
  {"id": "Austria"},
  {"id": "Greece"},
  {"id": "Japan"}],
"gdps": {"2000": {"Brazil": 644701831101.3938, "Canada": 724918860682.78223, "Italy": 1104009462562.1892, "Czech Republic": 58807244367.866722, "Luxembourg": 20267551133.222778, "France": 1326334899576.1931, "Slovak Republic": 28724041827.897552, "Ireland": 97452184611.203247, "Norway": 168288531891.20407, "Israel": 124895151203.00198, "Australia": 415774037555.737, "Iceland": 8697298233.8200874, "Germany": 1886401326699.8342, "Chile": 79328640263.789688, "Belgium": 232672747374.23993, "Spain": 580345494748.47986, "Netherlands": 385074626865.67169, "Denmark": 160082517845.87598, "Poland": 171276118424.23154, "Finland": 121793808734.10725, "Turkey": 266567531989.76328, "United States": 9898800000000.0, "Russian Federation": 259708496267.33026, "Sweden": 247260155857.7634, "Japan": 4731198760271.1445, "Switzerland": 256042925982.35431, "New Zealand": 51613868879.81382, "Portugal": 117299520913.94878, "Estonia": 5675174661.8758068, "Mexico": 581426421971.45312, "United Kingdom": 1475705855651.3843, "Austria": 192070749953.93405, "Greece": 124418164455.20268, "Hungary": 46385589533.836304}, "2001": {"Brazil": 553582178386.19165, "Canada": 715423553719.0083, "Italy": 1123702691037.1365, "Czech Republic": 64375288106.776917, "Luxembourg": 20196868008.948547, "France": 1338302818791.9463, "Slovak Republic": 30318731991.051456, "Ireland": 105273201630.42506, "Norway": 170922851073.76804, "Israel": 122940533086.0499, "Australia": 379357625845.22919, "Iceland": 7922983042.6606836, "Germany": 1880894854586.1299, "Chile": 72336972322.393127, "Belgium": 232485906040.26846, "Spain": 608856375838.92615, "Netherlands": 400654138702.46088, "Denmark": 160476161868.6019, "Poland": 190420870074.98962, "Finland": 124642505592.84117, "Turkey": 196005288838.12009, "United States": 10233900000000.0, "Russian Federation": 306602673980.11652, "Sweden": 227359498891.48135, "Japan": 4159859918093.5566, "Switzerland": 262647169329.8175, "New Zealand": 52885795370.835419, "Portugal": 120332080536.91277, "Estonia": 6237914200.4474277, "Mexico": 622092637151.15723, "United Kingdom": 1468026486253.0588, "Austria": 191678678299.77631, "Greece": 129841697351.14452, "Hungary": 52720966883.371872}, "2002": {"Brazil": 504221228974.03528, "Canada": 734661951188.42798, "Italy": 1225176959595.3323, "Czech Republic": 78425201660.629868, "Luxembourg": 22568793525.315266, "France": 1452030303030.303, "Slovak Republic": 34638306041.784302, "Ireland": 123167099019.38641, "Norway": 191927027230.14105, "Israel": 112974376292.79413, "Australia": 395012557555.46252, "Iceland": 8907207933.0298271, "Germany": 2006587615283.2676, "Chile": 70984568428.578537, "Belgium": 252795031055.90063, "Spain": 686295878035.00842, "Netherlands": 437807265198.56958, "Denmark": 173880831443.88007, "Poland": 198179425151.28568, "Finland": 135183512140.03387, "Turkey": 232534560774.9469, "United States": 10590200000000.0, "Russian Federation": 345110438693.57257, "Sweden": 250960758336.67108, "Japan": 3980819536159.7598, "Switzerland": 286658255888.61798, "New Zealand": 65477781211.493919, "Portugal": 132285714285.71429, "Estonia": 7318186726.8962917, "Mexico": 649075575301.6814, "United Kingdom": 1601617206235.012, "Austria": 207537336721.24976, "Greece": 146050256230.41409, "Hungary": 66389489264.339073}, "2003": {"Brazil": 552469288267.79333, "Canada": 865873242452.35889, "Italy": 1514503536381.4897, "Czech Republic": 95292530752.596695, "Luxembourg": 29144582392.776524, "France": 1792214221218.9617, "Slovak Republic": 45837416478.555305, "Ireland": 158947453566.59143, "Norway": 224880794327.84387, "Israel": 118673283414.94479, "Australia": 466474082702.38788, "Iceland": 10969898924.063669, "Germany": 2423814898419.8647, "Chile": 77840186384.822403, "Belgium": 311689616252.82166, "Spain": 883839729119.63879, "Netherlands": 538312641083.52142, "Denmark": 212621855882.93335, "Poland": 216800888642.04388, "Finland": 164256207674.94357, "Turkey": 303005302818.30902, "United States": 11089300000000.0, "Russian Federation": 430347770733.15521, "Sweden": 314713404152.70276, "Japan": 4302939184963.7939, "Switzerland": 334574926429.04877, "New Zealand": 86751097349.456451, "Portugal": 161931941309.25507, "Estonia": 9840743037.2460499, "Mexico": 700324664926.97156, "United Kingdom": 1855666938775.51, "Austria": 253945776523.70203, "Greece": 192850219244.13544, "Hungary": 83538373060.690598}, "2004": {"Brazil": 663760341880.34192, "Canada": 992226099521.91357, "Italy": 1735521503771.5818, "Czech Republic": 113976672924.83389, "Luxembourg": 34077095478.447662, "France": 2055678853687.4585, "Slovak Republic": 56073225726.347153, "Ireland": 186492264265.27103, "Norway": 260029106207.98923, "Israel": 126571173583.22177, "Australia": 611491677336.7478, "Iceland": 13251434311.421436, "Germany": 2726341472500.0464, "Chile": 100630707851.8593, "Belgium": 361683211959.79462, "Spain": 1044612070303.527, "Netherlands": 609889925685.86914, "Denmark": 244727978020.58401, "Poland": 252768998589.2543, "Finland": 189064585622.66797, "Turkey": 392166274991.23114, "United States": 11797800000000.0, "Russian Federation": 591016690742.93652, "Sweden": 362089648912.96509, "Japan": 4655803055650.5508, "Switzerland": 374224186243.66705, "New Zealand": 102238013445.37814, "Portugal": 185397304327.85135, "Estonia": 12025943709.994846, "Mexico": 759777472170.45129, "United Kingdom": 2196860009520.6709, "Austria": 291430382497.37695, "Greece": 227950420085.70898, "Hungary": 101925734602.02652}, "2005": {"Brazil": 882185702547.24731, "Canada": 1133759985475.6719, "Italy": 1786275014006.616, "Czech Republic": 130052420701.16861, "Luxembourg": 37643013480.575043, "France": 2136555489230.4634, "Slovak Republic": 61328471583.136421, "Ireland": 202752241478.88376, "Norway": 304060069848.66125, "Israel": 133959001782.53119, "Australia": 692353781386.25769, "Iceland": 16286323127.432255, "Germany": 2766253792966.2241, "Chile": 124404150138.16219, "Belgium": 377350395463.36371, "Spain": 1130798885738.447, "Netherlands": 638470626274.68542, "Denmark": 257675536234.49411, "Poland": 303912247950.84503, "Finland": 195777993334.32822, "Turkey": 482979839237.86847, "United States": 12564300000000.0, "Russian Federation": 764000901160.57983, "Sweden": 370579639747.4137, "Japan": 4571875737175.416, "Switzerland": 384753967478.59747, "New Zealand": 113094660704.22536, "Portugal": 191847858528.57785, "Estonia": 13905561150.077105, "Mexico": 848947464608.97754, "United Kingdom": 2295844712162.5898, "Austria": 304983601949.95776, "Greece": 240075690332.28873, "Hungary": 110321711572.90845}, "2006": {"Brazil": 1088916819852.941, "Canada": 1278610846644.8042, "Italy": 1872982702430.3103, "Czech Republic": 148345088495.57523, "Luxembourg": 42544669010.877625, "France": 2255705477450.0371, "Slovak Republic": 69002095094.718353, "Ireland": 222958270102.77982, "Norway": 340041912703.69684, "Israel": 145479599622.96332, "Australia": 744959568733.15369, "Iceland": 16651492783.542318, "Germany": 2902748698160.0493, "Chile": 154412421261.42474, "Belgium": 399965627160.06329, "Spain": 1236352163544.467, "Netherlands": 677691901432.74524, "Denmark": 274376889678.11151, "Poland": 341669943593.87592, "Finland": 207949409201.13254, "Turkey": 530900095204.76019, "United States": 13314500000000.0, "Russian Federation": 989930542278.68408, "Sweden": 399075661572.86615, "Japan": 4356761451087.2832, "Switzerland": 405183914852.77228, "New Zealand": 109333766233.76624, "Portugal": 201790398436.41214, "Estonia": 16798495347.749018, "Mexico": 951915698648.08801, "United Kingdom": 2452969436251.4648, "Austria": 324954402044.30585, "Greece": 261713232775.63193, "Hungary": 112533152716.38387}, "2007": {"Brazil": 1366853244424.2834, "Canada": 1424065729447.9099, "Italy": 2127180496503.0562, "Czech Republic": 180511237062.59241, "Luxembourg": 51320626630.42437, "France": 2582389733356.3267, "Slovak Republic": 84108560087.599228, "Ireland": 258307438734.36639, "Norway": 393479162081.79578, "Israel": 167111803510.13849, "Australia": 850516605166.05164, "Iceland": 20428232684.271328, "Germany": 3323807412152.1191, "Chile": 172868468116.17621, "Belgium": 459618853659.40454, "Spain": 1441426534070.2236, "Netherlands": 782566743038.27612, "Denmark": 311417601998.64062, "Poland": 425321502150.57648, "Finland": 246127357186.45895, "Turkey": 647155133931.99792, "United States": 13961800000000.0, "Russian Federation": 1299705764824.4817, "Sweden": 462512853670.12042, "Japan": 4356329296669.3276, "Switzerland": 450528109859.46008, "New Zealand": 134864705882.35294, "Portugal": 231741573802.62183, "Estonia": 21993658963.809711, "Mexico": 1036000680566.7072, "United Kingdom": 2825526440056.666, "Austria": 375041784029.84784, "Greece": 305431771154.79895, "Hungary": 136102020866.70837}, "2008": {"Brazil": 1653538618144.7991, "Canada": 1502678437546.8586, "Italy": 2307311495086.2417, "Czech Republic": 225448799062.68307, "Luxembourg": 54742739956.787636, "France": 2831794045482.8433, "Slovak Republic": 97908891167.423462, "Ireland": 262030325150.32773, "Norway": 453885460992.90784, "Israel": 201661649944.25864, "Australia": 1052255352166.7897, "Iceland": 16832079676.524397, "Germany": 3623686234298.8975, "Chile": 179626662207.08914, "Belgium": 507379060314.20514, "Spain": 1593420002197.2388, "Netherlands": 870811147324.86169, "Denmark": 343881383958.43182, "Poland": 529432301178.81458, "Finland": 271974219064.70868, "Turkey": 730337495966.19275, "United States": 14219300000000.0, "Russian Federation": 1660846387626.0032, "Sweden": 486158607819.63556, "Japan": 4849208099923.5674, "Switzerland": 524289203562.03082, "New Zealand": 130000000000.0, "Portugal": 251925293880.68991, "Estonia": 23781539698.978283, "Mexico": 1093096181804.3997, "United Kingdom": 2648935779074.4277, "Austria": 414171069689.0907, "Greece": 341593975533.01349, "Hungary": 154233541852.26819}, "2009": {"Brazil": 1620165226993.7656, "Canada": 1337577639751.5527, "Italy": 2111148008711.6218, "Czech Republic": 197218205666.31689, "Luxembourg": 50047718738.669403, "France": 2619685000757.1094, "Slovak Republic": 87239747151.986664, "Ireland": 224042002433.86404, "Norway": 378849392446.00714, "Israel": 194866363197.11108, "Australia": 923499434130.92078, "Iceland": 12115001166.607353, "Germany": 3298635952561.8779, "Chile": 171956957320.4993, "Belgium": 473351828106.96222, "Spain": 1455956368263.6353, "Netherlands": 796333367137.00073, "Denmark": 310544743670.3371, "Poland": 430917310342.61725, "Finland": 239382754295.03378, "Turkey": 614553921823.29163, "United States": 13898300000000.0, "Russian Federation": 1222648134225.4548, "Sweden": 405782994635.35858, "Japan": 5035141567658.8994, "Switzerland": 509467163036.92535, "New Zealand": 116481875000.0, "Portugal": 234119384365.75754, "Estonia": 19117606972.631531, "Mexico": 884351745752.58557, "United Kingdom": 2183862761501.0615, "Austria": 383626706101.19153, "Greece": 321016154721.23779, "Hungary": 126631684032.78262}, "2010": {"Brazil": 2143035333258.2432, "Canada": 1577040082217.7634, "Italy": 2041954747600.0, "Czech Republic": 198475392670.15704, "Luxembourg": 52507236842.105263, "France": 2548315434210.5264, "Slovak Republic": 87077443708.609268, "Ireland": 205903504498.6842, "Norway": 421236092715.23181, "Israel": 217443434073.28165, "Australia": 1138262493185.271, "Iceland": 12564460546.007854, "Germany": 3284473684210.5264, "Chile": 217556231840.97949, "Belgium": 468511842105.26312, "Spain": 1380109210526.3157, "Netherlands": 774657894736.84204, "Denmark": 313365836298.93237, "Poland": 469736810690.71863, "Finland": 235257894736.8421, "Turkey": 731144392556.33887, "United States": 14419400000000.0, "Russian Federation": 1524916698233.3093, "Sweden": 462903051317.61444, "Japan": 5495379357484.6201, "Switzerland": 552224618426.9231, "New Zealand": 139767625899.28058, "Portugal": 227446710526.3158, "Estonia": 18845656094.736843, "Mexico": 1035071158245.7336, "United Kingdom": 2256260000000.0, "Austria": 376837981578.94739, "Greece": 292304602598.6842, "Hungary": 128631634125.22844}, "2011": {"Brazil": 2476652189879.7202, "Canada": 1777788888888.8889, "Italy": 2192357094734.7224, "Czech Republic": 216011355932.2034, "Luxembourg": 59200833333.333336, "France": 2779719500000.0, "Slovak Republic": 96063803169.307755, "Ireland": 220823245966.66669, "Norway": 491064821428.57147, "Israel": 242928731134.71213, "Australia": 1384145284186.895, "Iceland": 14074764558.188873, "Germany": 3600833333333.3335, "Chile": 251190532752.35568, "Belgium": 513862500000.0, "Spain": 1476881944444.4446, "Netherlands": 836073611111.11108, "Denmark": 333616014897.57916, "Poland": 515666869136.80231, "Finland": 263179166666.66669, "Turkey": 774775177386.14612, "United States": 14991300000000.0, "Russian Federation": 1899085300762.05, "Sweden": 539277966101.69489, "Japan": 5896794887858.6641, "Switzerland": 659307920844.94385, "New Zealand": 0.0, "Portugal": 237573750000.0, "Estonia": 22154665058.333336, "Mexico": 1158146656760.6604, "United Kingdom": 2444883870967.7422, "Austria": 417656162500.0, "Greece": 289627362870.83337, "Hungary": 138696911369.74039}, "2012": {"Brazil": 2252664120777.3896, "Canada": 1821424139311.4492, "Italy": 2013263114238.8787, "Czech Republic": 195656544502.6178, "Luxembourg": 57117125224.993568, "France": 2612878387760.3496, "Slovak Republic": 91619230769.230759, "Ireland": 210330986079.96912, "Norway": 499667211001.28925, "Israel": 0.0, "Australia": 1520608083022.0979, "Iceland": 13656532879.676502, "Germany": 3399588583183.3374, "Chile": 268313656098.7959, "Belgium": 483709179737.72174, "Spain": 1349350732836.2046, "Netherlands": 772226793520.18506, "Denmark": 314242037116.96155, "Poland": 489795486644.15106, "Finland": 250024427873.48932, "Turkey": 789257487307.02917, "United States": 15684800000000.0, "Russian Federation": 2014774938341.8474, "Sweden": 525742140221.40216, "Japan": 5959718262199.1348, "Switzerland": 632193558707.47571, "New Zealand": 0.0, "Portugal": 212454101311.39108, "Estonia": 21854197100.797119, "Mexico": 1177271329643.8591, "United Kingdom": 2435173775671.4058, "Austria": 399649131196.96576, "Greece": 249098684277.44919, "Hungary": 125507525410.47693}},
    "privateDebt": {"2000": {"Brazil": 31.658735890797228, "Canada": 95.674810069321552, "Italy": 75.514657334512961, "Czech Republic": 47.24533472559088, "Luxembourg": 102.25743690450216, "France": 85.131472622434543, "Slovak Republic": 51.060933661086402, "Ireland": 104.61112475842694, "Norway": 65.499830547608013, "Israel": 76.769717321079654, "Australia": 87.61940344723935, "Iceland": 97.060861813283466, "Germany": 119.44644688644688, "Chile": 69.802603397251403, "Belgium": 77.831102030149324, "Spain": 97.773163339985118, "Netherlands": 134.20159823906596, "Denmark": 135.3288308862, "Poland": 26.576188377410404, "Finland": 53.150270433828815, "Turkey": 17.752138674441596, "United States": 168.40549307356446, "Russian Federation": 13.645696452036793, "Sweden": 42.317961973950396, "Japan": 219.28225395206528, "Switzerland": 154.7030090084339, "New Zealand": 110.00535989949915, "Portugal": 126.27310278525474, "Estonia": 36.144866222339047, "Mexico": 18.311665862292006, "United Kingdom": 129.46619173295437, "Austria": 102.62067149492968, "Greece": 47.403554194936298, "Hungary": 32.457192930307073}, "2001": {"Brazil": 30.384001067795918, "Canada": 178.30623158924524, "Italy": 77.491099904760674, "Czech Republic": 39.089651578460291, "Luxembourg": 129.05626938413823, "France": 87.90170915996714, "Slovak Republic": 37.229089604766131, "Ireland": 109.7211192726372, "Norway": 70.015036889504572, "Israel": 84.94868011085947, "Australia": 88.422451707820827, "Iceland": 98.844061353961351, "Germany": 118.80060897283411, "Chile": 72.253362724994531, "Belgium": 75.949084498639351, "Spain": 101.18372068072023, "Netherlands": 135.29708686689105, "Denmark": 142.56321638560928, "Poland": 27.271402472407651, "Finland": 55.92010797771524, "Turkey": 15.351427589179007, "United States": 176.65959094798757, "Russian Federation": 16.837738718189541, "Sweden": 97.868438298276416, "Japan": 189.56407681875652, "Switzerland": 149.11514874914326, "New Zealand": 108.69314241797159, "Portugal": 133.40561652280675, "Estonia": 39.029597653452392, "Mexico": 15.664309980539908, "United Kingdom": 134.63128457657001, "Austria": 105.06677415204229, "Greece": 57.410125868581432, "Hungary": 33.280083006573932}, "2002": {"Brazil": 30.653703288737145, "Canada": 173.17717175309329, "Italy": 79.577268316090368, "Czech Republic": 29.56647049888414, "Luxembourg": 103.74203556059646, "France": 85.954011834905515, "Slovak Republic": 39.267158314148162, "Ireland": 108.7903978450972, "Norway": 74.740902516987788, "Israel": 89.764969640354977, "Australia": 91.398701408641386, "Iceland": 105.19766653050307, "Germany": 117.52166776099804, "Chile": 73.623762101947989, "Belgium": 74.043630407266775, "Spain": 105.71114749512518, "Netherlands": 141.16385147480514, "Denmark": 145.47484332395791, "Poland": 27.434744947302548, "Finland": 58.342731437004858, "Turkey": 14.521289914704338, "United States": 167.60161474005969, "Russian Federation": 17.991143481379058, "Sweden": 99.113040844972431, "Japan": 186.87550961941071, "Switzerland": 148.37006001701081, "New Zealand": 103.38059593266959, "Portugal": 135.90193416937711, "Estonia": 44.711617416074148, "Mexico": 17.707933109576615, "United Kingdom": 139.22285160289314, "Austria": 104.58026746157405, "Greece": 61.002750520300765, "Hungary": 34.989387955085903}, "2003": {"Brazil": 28.653790972218502, "Canada": 167.03114900982959, "Italy": 83.208547090801829, "Czech Republic": 30.48100391837081, "Luxembourg": 103.12515958810475, "France": 88.664236037770095, "Slovak Republic": 31.84525597332048, "Ireland": 113.77540883244717, "Norway": 77.44425783959376, "Israel": 85.659913035433419, "Australia": 99.403546728301635, "Iceland": 130.38636132987199, "Germany": 116.29471478463329, "Chile": 74.533831692025771, "Belgium": 73.808377118812857, "Spain": 113.17282225871621, "Netherlands": 147.99253582698216, "Denmark": 151.62080947305219, "Poland": 28.070051568155836, "Finland": 64.176017480811652, "Turkey": 14.546437011815867, "United States": 183.27356968589541, "Russian Federation": 21.243567057304027, "Sweden": 99.821287320712642, "Japan": 186.19965168221293, "Switzerland": 152.46684626411792, "New Zealand": 108.76062091068218, "Portugal": 135.37722073412388, "Estonia": 50.648042183992203, "Mexico": 16.004931309414189, "United Kingdom": 143.52997898989614, "Austria": 104.8129940183192, "Greece": 64.767394973659563, "Hungary": 42.709315839812696}, "2004": {"Brazil": 28.950712688141483, "Canada": 170.01757215475024, "Italy": 84.834729357479205, "Czech Republic": 31.340836249970984, "Luxembourg": 106.17061961413035, "France": 90.60670156377391, "Slovak Republic": 30.42509236318654, "Ireland": 133.36853891153169, "Norway": 77.281283946847125, "Israel": 85.118598534793364, "Australia": 103.14320376234913, "Iceland": 164.63137704945356, "Germany": 112.93250444049734, "Chile": 75.566690020978839, "Belgium": 71.189239478589855, "Spain": 124.86015590269275, "Netherlands": 157.83168832861006, "Denmark": 158.15595629458866, "Poland": 28.148437381697672, "Finland": 67.603404568321224, "Turkey": 17.278526942741497, "United States": 191.37509236595383, "Russian Federation": 24.316400949334742, "Sweden": 101.32982231580594, "Japan": 178.92353233002194, "Switzerland": 154.02523394145166, "New Zealand": 112.42620572742285, "Portugal": 135.93771452490583, "Estonia": 60.781325755795955, "Mexico": 15.213503133179751, "United Kingdom": 151.16224025549201, "Austria": 105.97090007606478, "Greece": 70.788577734281105, "Hungary": 45.937743678713467}, "2005": {"Brazil": 31.366304915209291, "Canada": 178.17564929085887, "Italy": 88.993057322486763, "Czech Republic": 35.387842837227574, "Luxembourg": 129.07712383752624, "France": 92.667080702681588, "Slovak Republic": 35.118931258600199, "Ireland": 159.90958386803439, "Norway": 80.859089850402299, "Israel": 89.849103804340587, "Australia": 108.95972046055404, "Iceland": 247.89674901889666, "Germany": 112.59485704010071, "Chile": 76.33080421749743, "Belgium": 73.759124688977877, "Spain": 145.65093071798245, "Netherlands": 165.04157520251962, "Denmark": 171.77977514419931, "Poland": 28.937498347404965, "Finland": 75.050975360321161, "Turkey": 22.248866056781178, "United States": 195.76290046355945, "Russian Federation": 27.507933868768369, "Sweden": 107.85697133829835, "Japan": 192.86825043708808, "Switzerland": 159.13436797731526, "New Zealand": 122.37937794029756, "Portugal": 140.71357313570414, "Estonia": 69.711729399346765, "Mexico": 16.551460393250458, "United Kingdom": 158.54297502989601, "Austria": 115.62797767935167, "Greece": 79.586774060614033, "Hungary": 51.249345827737791}, "2006": {"Brazil": 40.337360625862431, "Canada": 194.19369955288352, "Italy": 94.471830285482213, "Czech Republic": 39.420700179174432, "Luxembourg": 154.67018142896319, "France": 98.431339765238192, "Slovak Republic": 38.681821461480716, "Ireland": 181.04342962614248, "Norway": 86.19218846241175, "Israel": 86.471580986936686, "Australia": 114.12866052467314, "Iceland": 319.46092980061331, "Germany": 109.60089027183544, "Chile": 77.8237761983616, "Belgium": 82.029238243698032, "Spain": 166.98422297465265, "Netherlands": 167.18997586150726, "Denmark": 185.6777672295498, "Poland": 33.291479211457023, "Finland": 78.79890206014538, "Turkey": 25.941625505726012, "United States": 205.7461952257118, "Russian Federation": 32.484803595104857, "Sweden": 112.80766043579851, "Japan": 188.68763161478387, "Switzerland": 163.68822645993518, "New Zealand": 132.14442253554586, "Portugal": 151.90475420781647, "Estonia": 82.802591596853233, "Mexico": 19.662141943986576, "United Kingdom": 170.15475296607977, "Austria": 116.37331195877836, "Greece": 85.243504173860472, "Hungary": 55.601855899576989}, "2007": {"Brazil": 47.853066405486629, "Canada": 127.41598900096693, "Italy": 100.56820889369575, "Czech Republic": 46.281862504856555, "Luxembourg": 184.76776684943781, "France": 105.5766574215038, "Slovak Republic": 42.419324860230425, "Ireland": 200.1470567942122, "Norway": 0.0, "Israel": 97.44729394387862, "Australia": 121.14812333312193, "Iceland": 261.38871090190946, "Germany": 105.25126621371217, "Chile": 83.928073589044615, "Belgium": 90.890817861024672, "Spain": 187.88665740565781, "Netherlands": 188.0639694424186, "Denmark": 202.50167525529946, "Poland": 39.443223082133052, "Finland": 81.523105154868489, "Turkey": 29.496044063524092, "United States": 213.92487390606226, "Russian Federation": 38.809519109580442, "Sweden": 121.47412458917384, "Japan": 181.12401925083316, "Switzerland": 167.31855876765624, "New Zealand": 137.12624307584943, "Portugal": 162.49663357729071, "Estonia": 91.329837696455201, "Mexico": 21.750093348889369, "United Kingdom": 186.34930908797347, "Austria": 115.4387472153972, "Greece": 93.912414923346958, "Hungary": 62.566016029147434}, "2008": {"Brazil": 53.095763758544933, "Canada": 128.24788769990107, "Italy": 104.75138343133077, "Czech Republic": 50.58001861027838, "Luxembourg": 193.71178571906401, "France": 108.76316150207299, "Slovak Republic": 44.988957405431243, "Ireland": 221.6377234405727, "Norway": 0.0, "Israel": 99.783364693004884, "Australia": 122.15954642233397, "Iceland": 126.66083360949538, "Germany": 108.61472228959495, "Chile": 92.18958395907967, "Belgium": 93.902562251894622, "Spain": 202.83998352620182, "Netherlands": 193.15621525330496, "Denmark": 216.31701073266893, "Poland": 49.638328500096783, "Finland": 85.98373458286207, "Turkey": 32.594105703877993, "United States": 194.62618167132771, "Russian Federation": 42.187328594527443, "Sweden": 127.64324412043742, "Japan": 176.05072371961174, "Switzerland": 157.824977572612, "New Zealand": 148.33274647887325, "Portugal": 173.69090335038732, "Estonia": 96.396187915693403, "Mexico": 20.966046089791281, "United Kingdom": 211.43011011630674, "Austria": 120.29387619521226, "Greece": 97.406634758230922, "Hungary": 69.799110957882405}, "2009": {"Brazil": 48.867117903800199, "Canada": 0.0, "Italy": 110.96982428948996, "Czech Republic": 52.020242730805357, "Luxembourg": 194.39329406409172, "France": 111.54838735712931, "Slovak Republic": 0.0, "Ireland": 233.54880989197972, "Norway": 0.0, "Israel": 93.549471591717321, "Australia": 123.20558832357192, "Iceland": 113.63033979270949, "Germany": 113.40795957043588, "Chile": 70.68704431807673, "Belgium": 97.469324028068399, "Spain": 212.11256989103674, "Netherlands": 214.15265990387886, "Denmark": 223.87316117948811, "Poland": 50.394899952406277, "Finland": 93.887463874928912, "Turkey": 36.484605915605947, "United States": 205.50725624138707, "Russian Federation": 46.152495998903262, "Sweden": 136.23377626948377, "Japan": 183.4379345190705, "Switzerland": 168.8139505935537, "New Zealand": 148.1256204023158, "Portugal": 186.78068845042876, "Estonia": 107.98453146764182, "Mexico": 23.069539053583092, "United Kingdom": 212.60908584015556, "Austria": 126.03285929086934, "Greece": 94.284160701189833, "Hungary": 69.50707824799926}, "2010": {"Brazil": 54.38481799448315, "Canada": 0.0, "Italy": 122.89462509041486, "Czech Republic": 53.09527075507534, "Luxembourg": 187.12463736327072, "France": 114.20986556480219, "Slovak Republic": 0.0, "Ireland": 214.36651064749478, "Norway": 0.0, "Israel": 95.652788661055496, "Australia": 126.35954158619067, "Iceland": 108.74474812957156, "Germany": 106.92893197660445, "Chile": 66.496203349898934, "Belgium": 94.420182605056894, "Spain": 214.39245368644549, "Netherlands": 199.35132656180997, "Denmark": 215.83104122613159, "Poland": 51.913005168132131, "Finland": 95.674959171346117, "Turkey": 44.206969515137537, "United States": 201.40521493067604, "Russian Federation": 43.801422974680129, "Sweden": 135.40284719452794, "Japan": 175.04776273859602, "Switzerland": 167.40145901315029, "New Zealand": 149.03339046824894, "Portugal": 190.6854989167503, "Estonia": 98.429936504795606, "Mexico": 24.706684127246817, "United Kingdom": 202.46652565204911, "Austria": 122.29114266913801, "Greece": 118.64606018981763, "Hungary": 68.795533979754936}, "2011": {"Brazil": 61.349925853161039, "Canada": 0.0, "Italy": 122.48720570630287, "Czech Republic": 55.634106911621352, "Luxembourg": 170.6940130229961, "France": 115.89503705120048, "Slovak Republic": 0.0, "Ireland": 204.26530540442567, "Norway": 0.0, "Israel": 95.093590554061848, "Australia": 123.44448256669691, "Iceland": 97.001391850620848, "Germany": 104.50578569775514, "Chile": 70.438231337213637, "Belgium": 92.572861849662544, "Spain": 205.888155883971, "Netherlands": 198.36055769943169, "Denmark": 208.40633473958957, "Poland": 54.817622512052665, "Finland": 96.6536316092227, "Turkey": 49.973310662482298, "United States": 192.29134032061262, "Russian Federation": 45.814867048329745, "Sweden": 135.88239596744378, "Japan": 174.8172635773162, "Switzerland": 169.36245381329363, "New Zealand": 0.0, "Portugal": 192.1800891068329, "Estonia": 84.720055099115299, "Mexico": 25.98424361388804, "United Kingdom": 186.86103227754072, "Austria": 119.75760084708436, "Greece": 121.87691293737093, "Hungary": 65.647675366928851}, "2012": {"Brazil": 68.372192263552591, "Canada": 0.0, "Italy": 124.42659360204604, "Czech Republic": 56.908872184219881, "Luxembourg": 165.21130742340583, "France": 115.96347484302747, "Slovak Republic": 0.0, "Ireland": 186.1237686019951, "Norway": 0.0, "Israel": 0.0, "Australia": 123.32488799996879, "Iceland": 96.778097016275538, "Germany": 101.93850692080781, "Chile": 73.245924371071752, "Belgium": 92.16886523899008, "Spain": 188.82694552297468, "Netherlands": 200.24207592593211, "Denmark": 205.79443339283077, "Poland": 53.781007643939041, "Finland": 98.241364947626622, "Turkey": 54.39521741379788, "United States": 193.59052794381057, "Russian Federation": 47.775320066396667, "Sweden": 138.47319817524507, "Japan": 176.73178223237326, "Switzerland": 176.1465627837517, "New Zealand": 0.0, "Portugal": 184.15727263704954, "Estonia": 79.255476197999883, "Mexico": 27.687025839377583, "United Kingdom": 178.72070515425261, "Austria": 116.98291756055208, "Greece": 120.70826293295272, "Hungary": 56.361005776319516}},
    "surplus":{"2000": {"Brazil": -1.8341213841722048, "Canada": 2.2816760900520814, "Italy": -0.78119531886710125, "Czech Republic": -3.4611698928710686, "Luxembourg": 5.5149909038209284, "France": -1.6178061201417973, "Slovak Republic": 0.0, "Ireland": 4.8764164011062947, "Norway": 15.728625032236462, "Israel": -3.5803149577665989, "Australia": 2.0110658467729143, "Iceland": 2.7103015407986089, "Germany": 1.3645909645909646, "Chile": -0.62406231564558223, "Belgium": 0.018967066994531625, "Spain": -0.46879936244556736, "Netherlands": 1.9573643410852715, "Denmark": 1.5849757682406682, "Poland": 0.0, "Finland": 6.788456446915542, "Turkey": 0.0, "United States": 0.0, "Russian Federation": 0.0, "Sweden": 3.5253528332377675, "Japan": 0.0, "Switzerland": 2.132952612004571, "New Zealand": 0.0, "Portugal": -2.5568954317926371, "Estonia": 0.19968068694473981, "Mexico": -1.1703727727345514, "United Kingdom": 3.8972863567293556, "Austria": -1.9793058489633544, "Greece": -3.7639730269562057, "Hungary": -2.8131612637650396}, "2001": {"Brazil": -2.0795582367578325, "Canada": 1.5974939713803014, "Italy": -2.9193993561801141, "Czech Republic": -3.9082610696830824, "Luxembourg": 5.7741827138799051, "France": -1.732335334866679, "Slovak Republic": 0.0, "Ireland": 1.4249745498978417, "Norway": 14.11645748841652, "Israel": -5.8988791824763798, "Australia": 0.83378719611823549, "Iceland": -0.06007982765249175, "Germany": -1.5357533660021885, "Chile": -0.50675340402572921, "Belgium": -0.27224473928322612, "Spain": 0.15902480463611687, "Netherlands": -0.17019147657857062, "Denmark": 0.83497365625170794, "Poland": -2.7886100435628123, "Finland": 5.5532422032048698, "Turkey": 0.0, "United States": 0.48446828677239373, "Russian Federation": 0.0, "Sweden": 1.8293583896229764, "Japan": 0.0, "Switzerland": 0.30389625938257298, "New Zealand": 1.677578507474824, "Portugal": -3.9238840167143718, "Estonia": 0.80477769762011797, "Mexico": 0.0, "United Kingdom": 0.75335494460884966, "Austria": -0.86523903540789127, "Greece": -4.6251468134122042, "Hungary": -4.2495652446805456}, "2002": {"Brazil": -1.1668070578038501, "Canada": 1.5672583604026351, "Italy": -2.3745018995799225, "Czech Republic": -5.7574010819737262, "Luxembourg": 1.8710476737698916, "France": -3.3964008935222743, "Slovak Republic": 0.0, "Ireland": 0.033030923142276077, "Norway": 9.1374639677297047, "Israel": -7.2174688737919768, "Australia": -0.43009584766103098, "Iceland": -1.2436028652259046, "Germany": -2.0467123159178313, "Chile": -1.175402265312296, "Belgium": 0.21100439282257466, "Spain": 0.31621182078221971, "Netherlands": -1.6229090268134665, "Denmark": 0.29510386913152337, "Poland": -4.5004934588870826, "Finland": 4.5159628531250435, "Turkey": 0.0, "United States": -2.6015372703065096, "Russian Federation": 7.0304009405678283, "Sweden": -0.88552685963095878, "Japan": 0.0, "Switzerland": 0.53658113138833408, "New Zealand": 1.658567800164426, "Portugal": -2.4916552130375025, "Estonia": 0.91817383727547353, "Mexico": 0.0, "United Kingdom": -1.978571943264031, "Austria": -1.401941495504808, "Greece": -4.8765085340717018, "Hungary": -8.1199503604533216}, "2003": {"Brazil": -4.3383510000455576, "Canada": 1.187297792981227, "Italy": -3.2053505033635141, "Czech Republic": -4.658668721148377, "Luxembourg": 0.20723418797154056, "France": -4.1317416480036737, "Slovak Republic": -3.1819186962164308, "Ireland": 0.11992690868400457, "Norway": 8.3049815946604735, "Israel": -7.3875618913135463, "Australia": 0.84825753867974474, "Iceland": -2.0636305069488858, "Germany": -2.2174621653084983, "Chile": -0.42823401375383729, "Belgium": -0.037297624177551177, "Spain": 0.68409183201759205, "Netherlands": -2.8290473744352074, "Denmark": -0.070322534124277414, "Poland": -5.4510671809250013, "Finland": 3.1738942218496402, "Turkey": 0.0, "United States": -3.8260755863760565, "Russian Federation": 2.2075553236602072, "Sweden": -0.91179617638171262, "Japan": 0.0, "Switzerland": -0.78525932936328957, "New Zealand": 2.8533136857228105, "Portugal": -2.6627829739244744, "Estonia": 1.9302897408679509, "Mexico": 0.0, "United Kingdom": -3.5127697088499348, "Austria": -1.8283617343916907, "Greece": -5.8022315435671699, "Hungary": -7.0940485576693701}, "2004": {"Brazil": -1.8550850806158024, "Canada": 1.5871023916536138, "Italy": -2.5928501716153147, "Czech Republic": -3.0718393209050183, "Luxembourg": -1.1222210545826381, "France": -3.4676840956097466, "Slovak Republic": -3.0049283381629377, "Ireland": 1.2871789769035149, "Norway": 11.672501101087853, "Israel": -5.8004819492876667, "Australia": 0.82732787752941661, "Iceland": 0.79694357011412476, "Germany": -2.3787402650635334, "Chile": 2.028875176730256, "Belgium": -0.23021968024662959, "Spain": -0.29395193594629226, "Netherlands": -1.5702873057754325, "Denmark": 1.9110204749757873, "Poland": -5.5000443464735902, "Finland": 3.0781658413565736, "Turkey": 0.0, "United States": -3.617725338622455, "Russian Federation": 5.2809174859037551, "Sweden": 0.38358380086562843, "Japan": 0.0, "Switzerland": -0.92508684726492607, "New Zealand": 3.6059248004877991, "Portugal": -3.301505232314776, "Estonia": 2.0794455247839654, "Mexico": 0.0, "United Kingdom": -3.1978171168640892, "Austria": -4.7696406208518907, "Greece": -7.3508868888248609, "Hungary": -6.1698905851424861}, "2005": {"Brazil": -3.5940946670608778, "Canada": 0.81515745953873975, "Italy": -3.65516225386434, "Czech Republic": -3.5682606474338074, "Luxembourg": 0.28520632927600531, "France": -2.7896210057117181, "Slovak Republic": -2.5948407351903509, "Ireland": 1.4276993010599677, "Norway": 15.11016092137095, "Israel": -4.7839828526881005, "Australia": 1.2550911051294886, "Iceland": 4.7955219667189271, "Germany": -2.3282682970688726, "Chile": 4.3381860826525909, "Belgium": -2.7480349992584903, "Spain": 1.6117928335925076, "Netherlands": -0.11199691472847079, "Denmark": 5.3756753730932783, "Poland": -4.0342641426540373, "Finland": 3.4313881178181913, "Turkey": 0.0, "United States": -2.8532508774862109, "Russian Federation": 9.8830683796861187, "Sweden": 1.5198375084631008, "Japan": -4.0589161009162478, "Switzerland": -0.41739711843737803, "New Zealand": 4.4027271179466183, "Portugal": -5.5218135629586556, "Estonia": 1.9612332543492503, "Mexico": 0.0, "United Kingdom": -3.0404447577036691, "Austria": -1.9824263252182586, "Greece": -5.5887173125835696, "Hungary": -7.3826328783220747}, "2006": {"Brazil": -2.8851689653827859, "Canada": 1.6280969798090879, "Italy": -2.4251333440459444, "Czech Republic": -4.0607301976764889, "Luxembourg": 1.1438172698855842, "France": -2.1827226298255442, "Slovak Republic": -3.0848340570052968, "Ireland": 2.7004626046952205, "Norway": 18.373065676327187, "Israel": -2.3833798274251774, "Australia": 1.7312114560468277, "Iceland": 5.9959222951941333, "Germany": -1.2844115994641083, "Chile": 7.3093838468727315, "Belgium": 0.19678260133174835, "Spain": 2.3278443341616382, "Netherlands": 0.56421875694166779, "Denmark": 5.5183098919565916, "Poland": -3.4110323188661464, "Finland": 4.4044279552378365, "Turkey": 1.9030911492600877, "United States": -1.9023695970558414, "Russian Federation": 8.0260944289643774, "Sweden": 2.085223876541868, "Japan": -0.86783359352026002, "Switzerland": 0.58424401417465721, "New Zealand": 4.7394490835877274, "Portugal": -3.931089661895093, "Estonia": 2.6249425258939079, "Mexico": 0.0, "United Kingdom": -2.7395873104218031, "Austria": -1.5845419681334545, "Greece": -5.9293743519664304, "Hungary": -8.5914634532656695}, "2007": {"Brazil": -1.8707572596800817, "Canada": 1.7330145548902351, "Italy": -1.4175148334561789, "Czech Republic": -1.508174717609724, "Luxembourg": 3.3112455929261659, "France": -2.3430165253980531, "Slovak Republic": -1.7150304744960161, "Ireland": 0.28487373089893542, "Norway": 17.848073550420668, "Israel": -1.2941715628324593, "Australia": 1.6359227289133325, "Iceland": 4.7926153994785059, "Germany": -0.32942145357216385, "Chile": 8.3605763869268497, "Belgium": -0.63695784881556805, "Spain": 2.4518568386030246, "Netherlands": 0.36500499324032437, "Denmark": 5.0645209241746416, "Poland": -1.8760351718353379, "Finland": 5.4779513985430679, "Turkey": 1.4104654408863289, "United States": -2.3018020599063158, "Russian Federation": 6.1860265633853695, "Sweden": 3.4232688359440031, "Japan": -2.4365505388954474, "Switzerland": 1.0852937958593973, "New Zealand": 3.0597112574693592, "Portugal": -2.5668618798104408, "Estonia": 2.838935584954704, "Mexico": 0.0, "United Kingdom": -2.6941072246744078, "Austria": -1.1107190915587155, "Greece": -6.7296989016763673, "Hungary": -4.9628264769706698}, "2008": {"Brazil": -1.2086943735575906, "Canada": 0.5753958106993935, "Italy": -2.2865212869588563, "Czech Republic": -1.4334227815064451, "Luxembourg": 2.7342129954371694, "France": -2.8551180817248127, "Slovak Republic": -2.028532160952965, "Ireland": -7.0020691594040994, "Norway": 20.009578446775947, "Israel": -3.6288578011327099, "Australia": 1.9113076342548121, "Iceland": -12.651825855791737, "Germany": -0.39130083272697874, "Chile": 4.5115783691429661, "Belgium": -1.23126669072537, "Spain": -2.3279352226720649, "Netherlands": 0.94620349514955071, "Denmark": 3.7011052093600552, "Poland": -3.6982903208077906, "Finland": 4.7692141972316477, "Turkey": -2.1523116670427069, "United States": -5.3637520834358936, "Russian Federation": 5.6198572461022023, "Sweden": 2.2816385379737354, "Japan": -2.946553465787646, "Switzerland": 1.2594039183540626, "New Zealand": 3.2166847237269773, "Portugal": -3.2018320404737439, "Estonia": -2.2710106438521431, "Mexico": 0.0, "United Kingdom": -4.7140355783864738, "Austria": -1.0899532575792394, "Greece": -9.8530145139329601, "Hungary": -3.7623830556939861}, "2009": {"Brazil": -3.4699575143392476, "Canada": -1.4211388600934607, "Italy": -5.0002134769149258, "Czech Republic": -5.9282587106764897, "Luxembourg": -0.63254536334179357, "France": -7.248582086378021, "Slovak Republic": -7.3531236901022838, "Ireland": -13.911976845136934, "Norway": 11.611951324963377, "Israel": -6.4380144620413144, "Australia": -2.4420131500375111, "Iceland": -8.9514791641252085, "Germany": -2.2122552116234999, "Chile": -4.2284571731173974, "Belgium": -4.9665579813288172, "Spain": -8.5772761101463662, "Netherlands": -4.9402077681928001, "Denmark": -2.1083139615206723, "Poland": -6.1055179336991729, "Finland": -2.0305481725646768, "Turkey": -5.2542739726439507, "United States": -10.533928609973882, "Russian Federation": -4.2092684299270475, "Sweden": -0.69399412065851207, "Japan": -7.5777472748470878, "Switzerland": 0.0, "New Zealand": -0.22374725681570629, "Portugal": -9.3714383026798931, "Estonia": -1.5267036280941659, "Mexico": 0.0, "United Kingdom": -10.988163607998784, "Austria": -3.1234922152974005, "Greece": -15.571580482716598, "Hungary": -4.1459608772882781}, "2010": {"Brazil": -1.6686751865984173, "Canada": -1.9783233863184226, "Italy": -3.8488661590336752, "Czech Republic": -4.7434368800911662, "Luxembourg": -0.97204705830663041, "France": -7.0218213762917561, "Slovak Republic": -6.7908795947408906, "Ireland": -30.9304057882566, "Norway": 12.202830993300228, "Israel": -4.7173620963661245, "Australia": -4.0451437923416504, "Iceland": -9.2237151220074107, "Germany": -3.1495873728066663, "Chile": -0.42404889263786105, "Belgium": -3.2000258376887629, "Spain": -5.2274657897973364, "Netherlands": -4.1942113666474166, "Denmark": -2.5106239452710666, "Poland": -6.7314689768417049, "Finland": -2.6046443992035617, "Turkey": -2.9148113033507577, "United States": -10.383656740224975, "Russian Federation": -1.8657465292560387, "Sweden": -0.18969112197010304, "Japan": -6.7460307588719699, "Switzerland": 0.0, "New Zealand": -2.762550379097886, "Portugal": -8.9985913415230279, "Estonia": -0.068422859768233091, "Mexico": 0.0, "United Kingdom": -10.084489717156165, "Austria": -3.2576822960066885, "Greece": -10.578816804847611, "Hungary": -3.5880855680021679}, "2011": {"Brazil": -2.5822104818266181, "Canada": -1.2359581843522569, "Italy": -3.4975040317077486, "Czech Republic": -4.445858543218459, "Luxembourg": -0.40204653828862374, "France": -5.1438543429371997, "Slovak Republic": -4.8945323246041434, "Ireland": -13.294827415441604, "Norway": 14.508445386356108, "Israel": -4.410917901560496, "Australia": -3.6879722598953766, "Iceland": -5.2898279503043213, "Germany": -0.40075599784000615, "Chile": 1.2904211006808113, "Belgium": -3.5987253399498895, "Spain": -3.5164173770753884, "Netherlands": -3.9169530859357482, "Denmark": -1.9922211219758887, "Poland": -4.3074293815331597, "Finland": -0.48287763405791367, "Turkey": -1.2913867499942417, "United States": -9.346040703608093, "Russian Federation": 3.2970412692108693, "Sweden": 0.52184139381710515, "Japan": -8.269758056976368, "Switzerland": 0.0, "New Zealand": -7.3394268162790128, "Portugal": -4.0015351957959249, "Estonia": 1.0155874593796566, "Mexico": 0.0, "United Kingdom": -7.746855184097404, "Austria": -2.2310916259176872, "Greece": -9.7519944816266442, "Hungary": 3.627506468116843}}, "currentAccount":{"2000": {"Brazil": 0.0, "Canada": 0.0, "Italy": 0.0, "Czech Republic": 0.0, "Luxembourg": 0.0, "France": 0.0, "Slovak Republic": 0.0, "Ireland": 0.0, "Norway": 0.0, "Israel": 0.0, "Australia": 0.0, "Iceland": 0.0, "Germany": 0.0, "Chile": 0.0, "Belgium": 0.0, "Spain": 0.0, "Netherlands": 0.0, "Denmark": 0.0, "Poland": 0.0, "Finland": 0.0, "Turkey": 0.0, "United States": 0.0, "Russian Federation": 0.0, "Sweden": 0.0, "Japan": 0.0, "Switzerland": 0.0, "New Zealand": 0.0, "Portugal": 0.0, "Estonia": 0.0, "Mexico": 0.0, "United Kingdom": 0.0, "Austria": 0.0, "Greece": 0.0, "Hungary": 0.0}, "2001": {"Brazil": 0.0, "Canada": 0.0, "Italy": 0.0, "Czech Republic": 0.0, "Luxembourg": 0.0, "France": 0.0, "Slovak Republic": 0.0, "Ireland": 0.0, "Norway": 0.0, "Israel": 0.0, "Australia": 0.0, "Iceland": 0.0, "Germany": 0.0, "Chile": 0.0, "Belgium": 0.0, "Spain": 0.0, "Netherlands": 0.0, "Denmark": 0.0, "Poland": 0.0, "Finland": 0.0, "Turkey": 0.0, "United States": 0.0, "Russian Federation": 0.0, "Sweden": 0.0, "Japan": 0.0, "Switzerland": 0.0, "New Zealand": 0.0, "Portugal": 0.0, "Estonia": 0.0, "Mexico": 0.0, "United Kingdom": 0.0, "Austria": 0.0, "Greece": 0.0, "Hungary": 0.0}, "2002": {"Brazil": 0.0, "Canada": 0.0, "Italy": 0.0, "Czech Republic": 0.0, "Luxembourg": 0.0, "France": 0.0, "Slovak Republic": 0.0, "Ireland": 0.0, "Norway": 0.0, "Israel": 0.0, "Australia": 0.0, "Iceland": 0.0, "Germany": 0.0, "Chile": 0.0, "Belgium": 0.0, "Spain": 0.0, "Netherlands": 0.0, "Denmark": 0.0, "Poland": 0.0, "Finland": 0.0, "Turkey": 0.0, "United States": 0.0, "Russian Federation": 0.0, "Sweden": 0.0, "Japan": 0.0, "Switzerland": 0.0, "New Zealand": 0.0, "Portugal": 0.0, "Estonia": 0.0, "Mexico": 0.0, "United Kingdom": 0.0, "Austria": 0.0, "Greece": 0.0, "Hungary": 0.0}, "2003": {"Brazil": 0.0, "Canada": 0.0, "Italy": 0.0, "Czech Republic": 0.0, "Luxembourg": 0.0, "France": 0.0, "Slovak Republic": 0.0, "Ireland": 0.0, "Norway": 0.0, "Israel": 0.0, "Australia": 0.0, "Iceland": 0.0, "Germany": 0.0, "Chile": 0.0, "Belgium": 0.0, "Spain": 0.0, "Netherlands": 0.0, "Denmark": 0.0, "Poland": 0.0, "Finland": 0.0, "Turkey": 0.0, "United States": 0.0, "Russian Federation": 0.0, "Sweden": 0.0, "Japan": 0.0, "Switzerland": 0.0, "New Zealand": 0.0, "Portugal": 0.0, "Estonia": 0.0, "Mexico": 0.0, "United Kingdom": 0.0, "Austria": 0.0, "Greece": 0.0, "Hungary": 0.0}, "2004": {"Brazil": 0.0, "Canada": 0.0, "Italy": 0.0, "Czech Republic": 0.0, "Luxembourg": 0.0, "France": 0.0, "Slovak Republic": 0.0, "Ireland": 0.0, "Norway": 0.0, "Israel": 0.0, "Australia": 0.0, "Iceland": 0.0, "Germany": 0.0, "Chile": 0.0, "Belgium": 0.0, "Spain": 0.0, "Netherlands": 0.0, "Denmark": 0.0, "Poland": 0.0, "Finland": 0.0, "Turkey": 0.0, "United States": 0.0, "Russian Federation": 0.0, "Sweden": 0.0, "Japan": 0.0, "Switzerland": 0.0, "New Zealand": 0.0, "Portugal": 0.0, "Estonia": 0.0, "Mexico": 0.0, "United Kingdom": 0.0, "Austria": 0.0, "Greece": 0.0, "Hungary": 0.0}, "2005": {"Brazil": 13984655478.0, "Canada": 21576655512.0, "Italy": -29743940373.0, "Czech Republic": -1209609349.0, "Luxembourg": 4406364512.0, "France": -10260220352.0, "Slovak Republic": -4004660567.0, "Ireland": -7150388578.0, "Norway": 49967488000.0, "Israel": 4043100000.0, "Australia": -41728655540.0, "Iceland": -2647861889.0, "Germany": 140216000000.0, "Chile": 1448786756.0, "Belgium": 7702627141.0, "Spain": -83388150704.0, "Netherlands": 46618218495.0, "Denmark": 11103861630.0, "Poland": -7242000000.0, "Finland": 7788421393.0, "Turkey": -21449000000.0, "United States": -745778000000.0, "Russian Federation": 84388739335.0, "Sweden": 26423000887.0, "Japan": 165783000000.0, "Switzerland": 53148930717.0, "New Zealand": -8842491915.0, "Portugal": -19821281863.0, "Estonia": -1386395117.0, "Mexico": -5558227839.0, "United Kingdom": -59406046454.0, "Austria": 6245047787.0, "Greece": -18233177668.0, "Hungary": -8238318967.0}, "2006": {"Brazil": 13621476250.0, "Canada": 17931696702.0, "Italy": -47827994064.0, "Czech Republic": -3130375916.0, "Luxembourg": 4396623300.0, "France": -12988244366.0, "Slovak Republic": -3937492153.0, "Ireland": -7858842561.0, "Norway": 55913071665.0, "Israel": 6961000000.0, "Australia": -41379022798.0, "Iceland": -3989874760.0, "Germany": 182352000000.0, "Chile": 7154259466.0, "Belgium": 7545119712.0, "Spain": -110874000000.0, "Netherlands": 63068623752.0, "Denmark": 8218404334.0, "Poland": -13156000000.0, "Finland": 11562672227.0, "Turkey": -31836000000.0, "United States": -800611000000.0, "Russian Federation": 92315565694.0, "Sweden": 36296082191.0, "Japan": 171078000000.0, "Switzerland": 55847956016.0, "New Zealand": -9030658992.0, "Portugal": -21534380615.0, "Estonia": -2585466594.0, "Mexico": -6157872196.0, "United Kingdom": -81957621059.0, "Austria": 9042085561.0, "Greece": -29565324184.0, "Hungary": -8379522015.0}, "2007": {"Brazil": 1550785092.0, "Canada": 11360592838.0, "Italy": -51574277108.0, "Czech Republic": -7940202854.0, "Luxembourg": 5214581906.0, "France": -26610486267.0, "Slovak Republic": -4102586954.0, "Ireland": -13850436298.0, "Norway": 49732367558.0, "Israel": 5231200000.0, "Australia": -59091496339.0, "Iceland": -3194945645.0, "Germany": 248783000000.0, "Chile": 7458194607.0, "Belgium": 7041317236.0, "Spain": -144540000000.0, "Netherlands": 52525726269.0, "Denmark": 4413619699.0, "Poland": -26499000000.0, "Finland": 13292202028.0, "Turkey": -37781000000.0, "United States": -710299000000.0, "Russian Federation": 71347920076.0, "Sweden": 46703999580.0, "Japan": 211685000000.0, "Switzerland": 40383558170.0, "New Zealand": -10872122155.0, "Portugal": -23516499912.0, "Estonia": -3503236042.0, "Mexico": -12969845236.0, "United Kingdom": -71079401612.0, "Austria": 13189478052.0, "Greece": -44587281268.0, "Hungary": -9962005687.0}, "2008": {"Brazil": -28192023673.0, "Canada": 1788555276.0, "Italy": -65379585509.0, "Czech Republic": -4773718820.0, "Luxembourg": 3040018101.0, "France": -49876972217.0, "Slovak Republic": -6185476916.0, "Ireland": -15296913071.0, "Norway": 72915061387.0, "Israel": 2913600000.0, "Australia": -47858511040.0, "Iceland": -4472425702.0, "Germany": 226272000000.0, "Chile": -3307203209.0, "Belgium": -7109614255.0, "Spain": -154529000000.0, "Netherlands": 38035620795.0, "Denmark": 10000302161.0, "Poland": -34957000000.0, "Finland": 8941260212.0, "Turkey": -40438000000.0, "United States": -677140000000.0, "Russian Federation": 103935000000.0, "Sweden": 48877392670.0, "Japan": 159363000000.0, "Switzerland": 5747337690.0, "New Zealand": -11561399067.0, "Portugal": -31905824944.0, "Estonia": -2216564330.0, "Mexico": -18725078369.0, "United Kingdom": -41159056643.0, "Austria": 20127241172.0, "Greece": -51312803251.0, "Hungary": -11119053762.0}, "2009": {"Brazil": -24302262100.0, "Canada": -40587990192.0, "Italy": -40874283748.0, "Czech Republic": -4848934415.0, "Luxembourg": 3504731827.0, "France": -35439355228.0, "Slovak Republic": -3161067767.0, "Ireland": -5001369302.0, "Norway": 45169002359.0, "Israel": 8091200000.0, "Australia": -44783639831.0, "Iceland": -1407385271.0, "Germany": 199476000000.0, "Chile": 3517770523.0, "Belgium": -6560656214.0, "Spain": -69774759405.0, "Netherlands": 41574941203.0, "Denmark": 10767024186.0, "Poland": -17155000000.0, "Finland": 6681281385.0, "Turkey": -12168000000.0, "United States": -381896000000.0, "Russian Federation": 50383643240.0, "Sweden": 30385791736.0, "Japan": 147017000000.0, "Switzerland": 36119755823.0, "New Zealand": -3162784237.0, "Portugal": -25652161911.0, "Estonia": 682162597.10000002, "Mexico": -5767398044.0, "United Kingdom": -37050488123.0, "Austria": 10290939660.0, "Greece": -35912575298.0, "Hungary": -193389453.40000001}, "2010": {"Brazil": -47322968848.0, "Canada": -58413258758.0, "Italy": -72874751586.0, "Czech Republic": -7601855213.0, "Luxembourg": 4424928511.0, "France": -39788770639.0, "Slovak Republic": -3008940649.0, "Ireland": 2318686917.0, "Norway": 50258127256.0, "Israel": 8109300000.0, "Australia": -36742294341.0, "Iceland": -1012178027.0, "Germany": 207725000000.0, "Chile": 3223519676.0, "Belgium": 8423087277.0, "Spain": -62497726336.0, "Netherlands": 60963188249.0, "Denmark": 18336776260.0, "Poland": -24030000000.0, "Finland": 5901314425.0, "Turkey": -45447000000.0, "United States": -441955000000.0, "Russian Federation": 67452200733.0, "Sweden": 31699801134.0, "Japan": 203916000000.0, "Switzerland": 73462195628.0, "New Zealand": -4655607788.0, "Portugal": -24185972509.0, "Estonia": 549466945.70000005, "Mexico": -1948617570.0, "United Kingdom": -75228989931.0, "Austria": 13149148088.0, "Greece": -30273985654.0, "Hungary": 1401690575.0}, "2011": {"Brazil": -52480127065.0, "Canada": -52845667624.0, "Italy": -67142871500.0, "Czech Republic": -6113696972.0, "Luxembourg": 4199025877.0, "France": -54437029629.0, "Slovak Republic": 12400809.57, "Ireland": 2513804281.0, "Norway": 66693551598.0, "Israel": 3381900000.0, "Australia": -33753408377.0, "Iceland": -864277309.89999998, "Germany": 223324000000.0, "Chile": -3283075668.0, "Belgium": -5662097712.0, "Spain": -55066072763.0, "Netherlands": 84589930034.0, "Denmark": 18887181845.0, "Poland": -25023000000.0, "Finland": -1780586344.0, "Turkey": -75092000000.0, "United States": -465923000000.0, "Russian Federation": 97273935835.0, "Sweden": 37968665043.0, "Japan": 119064000000.0, "Switzerland": 35899786114.0, "New Zealand": -6686092592.0, "Portugal": -16760550807.0, "Estonia": 476973392.60000002, "Mexico": -9671245630.0, "United Kingdom": -32764906947.0, "Austria": 5518774479.0, "Greece": -28582720075.0, "Hungary": 1210870667.0}, "2012": {"Brazil": -54246393412.0, "Canada": -66998343092.0, "Italy": -15210846819.0, "Czech Republic": -4731132666.0, "Luxembourg": 3178159599.0, "France": -60097603450.0, "Slovak Republic": 0.0, "Ireland": 10160417667.0, "Norway": 0.0, "Israel": -198200000.0, "Australia": 0.0, "Iceland": -657540459.0, "Germany": 238457000000.0, "Chile": -9496520872.0, "Belgium": -6649458518.0, "Spain": -14816203923.0, "Netherlands": 76912614449.0, "Denmark": 17224968428.0, "Poland": -17360000000.0, "Finland": -3678451168.0, "Turkey": -47521000000.0, "United States": -474970000000.0, "Russian Federation": 74798447636.0, "Sweden": 37586757669.0, "Japan": 0.0, "Switzerland": 78839793436.0, "New Zealand": 0.0, "Portugal": -3365080137.0, "Estonia": -267789064.90000001, "Mexico": -9248578628.0, "United Kingdom": -90374313203.0, "Austria": 7084770720.0, "Greece": -8624494503.0, "Hungary": 1999576712.0}}
}